fds/__init__.py
fds/sdk/__init__.py
fds/sdk/FixedIncomeCalculation/__init__.py
fds/sdk/FixedIncomeCalculation/api_client.py
fds/sdk/FixedIncomeCalculation/configuration.py
fds/sdk/FixedIncomeCalculation/exceptions.py
fds/sdk/FixedIncomeCalculation/model_utils.py
fds/sdk/FixedIncomeCalculation/rest.py
fds/sdk/FixedIncomeCalculation/api/__init__.py
fds/sdk/FixedIncomeCalculation/api/discount_curves_api.py
fds/sdk/FixedIncomeCalculation/api/fi_calculations_api.py
fds/sdk/FixedIncomeCalculation/apis/__init__.py
fds/sdk/FixedIncomeCalculation/model/__init__.py
fds/sdk/FixedIncomeCalculation/model/calculation_info.py
fds/sdk/FixedIncomeCalculation/model/calculation_info_root.py
fds/sdk/FixedIncomeCalculation/model/calculation_meta.py
fds/sdk/FixedIncomeCalculation/model/client_error_response.py
fds/sdk/FixedIncomeCalculation/model/error.py
fds/sdk/FixedIncomeCalculation/model/error_source.py
fds/sdk/FixedIncomeCalculation/model/fi_attribution_for_job_settings.py
fds/sdk/FixedIncomeCalculation/model/fi_attribution_for_securities.py
fds/sdk/FixedIncomeCalculation/model/fi_balloon_extension.py
fds/sdk/FixedIncomeCalculation/model/fi_bank_loans.py
fds/sdk/FixedIncomeCalculation/model/fi_calculation_parameters.py
fds/sdk/FixedIncomeCalculation/model/fi_calculation_parameters_root.py
fds/sdk/FixedIncomeCalculation/model/fi_cashflows.py
fds/sdk/FixedIncomeCalculation/model/fi_convertible_settings.py
fds/sdk/FixedIncomeCalculation/model/fi_discount_curve_info.py
fds/sdk/FixedIncomeCalculation/model/fi_discount_curve_info_root.py
fds/sdk/FixedIncomeCalculation/model/fi_job_settings.py
fds/sdk/FixedIncomeCalculation/model/fi_loss.py
fds/sdk/FixedIncomeCalculation/model/fi_market_environment.py
fds/sdk/FixedIncomeCalculation/model/fi_municipal_bonds.py
fds/sdk/FixedIncomeCalculation/model/fi_municipal_bonds_for_job_settings.py
fds/sdk/FixedIncomeCalculation/model/fi_prepay.py
fds/sdk/FixedIncomeCalculation/model/fi_prepay_lockout.py
fds.sdk.FixedIncomeCalculation-1.2.2.dist-info/LICENSE
fds.sdk.FixedIncomeCalculation-1.2.2.dist-info/METADATA
fds.sdk.FixedIncomeCalculation-1.2.2.dist-info/WHEEL
fds.sdk.FixedIncomeCalculation-1.2.2.dist-info/top_level.txt
fds.sdk.FixedIncomeCalculation-1.2.2.dist-info/RECORD
